Metadata-Version: 1.0
Name: distributionsexerciseupload
Version: 1.4
Summary: Gaussian distributions
Home-page: UNKNOWN
Author: UNKNOWN
Author-email: UNKNOWN
License: UNKNOWN
Platform: UNKNOWN
